setup.py
pagseguro/__init__.py
pagseguro_api_v2.egg-info/PKG-INFO
pagseguro_api_v2.egg-info/SOURCES.txt
pagseguro_api_v2.egg-info/dependency_links.txt
pagseguro_api_v2.egg-info/not-zip-safe
pagseguro_api_v2.egg-info/requires.txt
pagseguro_api_v2.egg-info/top_level.txt