Metadata-Version: 1.1
Name: pagseguro-api-v2
Version: 0.0.2
Summary: Pagseguro API
Home-page: https://github.com/joffilyfe/pagseguro-api
Author: Joffily Ferreira
Author-email: contato@joffily.me
License: MIT
Keywords: pagseguro,pagseguro-api
Platform: UNKNOWN
Classifier: Environment :: Web Environment
Classifier: Intended Audience :: Developers
Classifier: Natural Language :: English
Classifier: License :: OSI Approved :: BSD License
Classifier: Programming Language :: Python
Classifier: Programming Language :: Python :: 3.5
